chemprobe/__init__.py
chemprobe/bio.py
chemprobe/chem.py
chemprobe/datasets.py
chemprobe/models.py
chemprobe/data/cpds.csv.gz
chemprobe-0.1.5.dist-info/LICENSE
chemprobe-0.1.5.dist-info/METADATA
chemprobe-0.1.5.dist-info/WHEEL
chemprobe-0.1.5.dist-info/top_level.txt
chemprobe-0.1.5.dist-info/RECORD
