Metadata-Version: 2.1
Name: chemprobe
Version: 0.1.5
Summary: A package for chemprobe
Home-page: https://github.com/keiserlab/chemprobe
Author: William Connell
Author-email: connell@keiserlab.org
License: UNKNOWN
Platform: UNKNOWN
Classifier: Programming Language :: Python :: 3
Classifier: License :: OSI Approved :: MIT License
Classifier: Operating System :: OS Independent
Requires-Python: >=3.7,<=3.11.0
Requires-Dist: pandas (==1.5.1)
Requires-Dist: scikit-learn (==1.1.3)
Requires-Dist: pytorch-lightning (==1.8.4)
Requires-Dist: optuna (==2.10.1)
Requires-Dist: rdkit (==2022.9.5)
Requires-Dist: thunor (==0.1.29)
Requires-Dist: kneed (==0.8.2)
Requires-Dist: captum (==0.7.0)
Requires-Dist: torchmetrics (==0.10.3)
Requires-Dist: gdown (==4.6.0)
